ghoshell_common-0.4.0.dist-info/METADATA
ghoshell_common-0.4.0.dist-info/WHEEL
ghoshell_common-0.4.0.dist-info/entry_points.txt
ghoshell_common-0.4.0.dist-info/licenses/LICENSE
ghoshell_common/__init__.py
ghoshell_common/cli/__init__.py
ghoshell_common/cli/main.py
ghoshell_common/contracts/__init__.py
ghoshell_common/contracts/assets.py
ghoshell_common/contracts/configs.py
ghoshell_common/contracts/logger.py
ghoshell_common/contracts/storage.py
ghoshell_common/contracts/workspace.py
ghoshell_common/entity.py
ghoshell_common/helpers/__init__.py
ghoshell_common/helpers/code_analyser.py
ghoshell_common/helpers/coding.py
ghoshell_common/helpers/dictionary.py
ghoshell_common/helpers/files.py
ghoshell_common/helpers/hashes.py
ghoshell_common/helpers/io.py
ghoshell_common/helpers/modules.py
ghoshell_common/helpers/openai.py
ghoshell_common/helpers/string.py
ghoshell_common/helpers/timeutils.py
ghoshell_common/helpers/toml.py
ghoshell_common/helpers/trans.py
ghoshell_common/helpers/tree_sitter.py
ghoshell_common/helpers/yaml.py
ghoshell_common/identifier.py
ghoshell_common/prompter.py
ghoshell_common-0.4.0.dist-info/RECORD
