Metadata-Version: 2.1
Name: ghoshell-common
Version: 0.4.0
Summary: common library for GhostInShells project
Author-Email: thirdgerb <thirdgerb@gmail.com>
License: MIT
Requires-Python: >=3.10
Requires-Dist: click>=8.3.0
Requires-Dist: ghoshell-container>=0.3.0
Requires-Dist: pydantic<3.0.0,>=2.7.0
Requires-Dist: pyyaml<7.0.0,>=6.0.1
Requires-Dist: tomlkit>=0.13.3
Requires-Dist: tree-sitter<=0.24.0,>=0.23.0
Requires-Dist: tree-sitter-languages>=1.10.0
Requires-Dist: tree-sitter-python>=0.23.6
